setup.cfg
setup.py
pystateful/__init__.py
pystateful/stateful.py
pystateful.egg-info/PKG-INFO
pystateful.egg-info/SOURCES.txt
pystateful.egg-info/dependency_links.txt
pystateful.egg-info/top_level.txt
pystateful/test/__init__.py
pystateful/test/test_stateful.py