Metadata-Version: 1.0
Name: pystateful
Version: 0.1.0
Summary: State Pattern toolkit
Home-page: UNKNOWN
Author: Alan Franzoni
Author-email: username@franzoni.eu
License: APL 2.0
Keywords: state pattern
Platform: UNKNOWN
